examples/__init__.py
examples/_mlkn_multigpu.py
examples/_mlkn_vision.py
examples/_mlkn_vision3l.py
examples/mlkn_classification.py
examples/mlkn_generic.py
kerNET-0.1.0.dist-info/DESCRIPTION.rst
kerNET-0.1.0.dist-info/METADATA
kerNET-0.1.0.dist-info/RECORD
kerNET-0.1.0.dist-info/WHEEL
kerNET-0.1.0.dist-info/metadata.json
kerNET-0.1.0.dist-info/top_level.txt
