Metadata-Version: 2.0
Name: kerNET
Version: 0.1.0
Summary: Connectionist models powered by kernel machines.
Home-page: https://github.com/michaelshiyu/kerNET.git
Author: michaelshiyu
Author-email: michaelshiyu3@gmail.com
License: MIT
Platform: UNKNOWN
Classifier: License :: OSI Approved :: MIT License
Classifier: Programming Language :: Python
Classifier: Programming Language :: Python :: 3
Classifier: Programming Language :: Python :: 3.6
Classifier: Programming Language :: Python :: Implementation :: CPython
Classifier: Programming Language :: Python :: Implementation :: PyPy
Requires-Python: >=3.6.0
Requires-Dist: pytorch (==0.4.0)
